zonecheck/__init__.py
zonecheck-1.4.0.data/scripts/axfrcheck
zonecheck-1.4.0.data/scripts/zonecheck
zonecheck-1.4.0.data/scripts/zonechecklite
zonecheck-1.4.0.dist-info/LICENSE
zonecheck-1.4.0.dist-info/METADATA
zonecheck-1.4.0.dist-info/WHEEL
zonecheck-1.4.0.dist-info/top_level.txt
zonecheck-1.4.0.dist-info/RECORD
