Metadata-Version: 2.1
Name: zonecheck
Version: 1.4.0
Summary: Helper libraries to check if DNS zonefiles configured on a server are the same as DNS master servers.
Home-page: https://github.com/icann-dns/zonecheck
Author: John Bond
Author-email: pypi@johnbond.org
License: License :: OSI Approved :: Apache Software License 2.0 (Apache-2.0)
Project-URL: Bug Tracker, https://github.com/icann-dns/zonecheck/issues
Keywords: dns,puppet
Classifier: Development Status :: 5 - Production/Stable
Classifier: Environment :: Console
Classifier: Intended Audience :: Developers
Classifier: Intended Audience :: System Administrators
Classifier: Intended Audience :: Information Technology
Classifier: License :: OSI Approved :: Apache Software License
Classifier: Natural Language :: English
Classifier: Operating System :: POSIX
Classifier: Programming Language :: Python :: 2.7
Classifier: Programming Language :: Python :: 3
Classifier: Programming Language :: Python :: 3.6
Classifier: Programming Language :: Python :: 3.7
Classifier: Programming Language :: Python :: 3.8
Classifier: Programming Language :: Python :: 3.9
Classifier: Topic :: Internet :: Name Service (DNS)
Classifier: Topic :: System :: Networking :: Monitoring
Classifier: Topic :: System :: Systems Administration
Classifier: Topic :: Utilities
License-File: LICENSE
Requires-Dist: pyyaml >=5.2
Requires-Dist: future
Requires-Dist: dnspython >=1.15 ; python_version < "3.0"
Requires-Dist: dnspython >=2.0.0 ; python_version >= "3.6"
